dynamodb/__init__.py
dynamodb/base.py
dynamodb/dynamodb.py
talkytimes/__init__.py
talkytimes/base.py
talkytimes/talkytimes.py
talkytimes_package-0.3.84.dist-info/LICENSE
talkytimes_package-0.3.84.dist-info/METADATA
talkytimes_package-0.3.84.dist-info/WHEEL
talkytimes_package-0.3.84.dist-info/top_level.txt
talkytimes_package-0.3.84.dist-info/RECORD
