Metadata-Version: 2.1
Name: talkytimes-package
Version: 0.3.84
Summary: Talkytimes package
Home-page: https://github.com/Steven339/talkytimes-package
Author: Steven Correa
Author-email: brayancorrea78@gmail.com
Requires-Python: >=3.10
License-File: LICENSE
Requires-Dist: selenium
Requires-Dist: beautifulsoup4
Requires-Dist: html5lib
Requires-Dist: boto3
Requires-Dist: pytz
